[
  {
    "data": {
      "id": "1",
      "label": "IP 1",
      "type": "ip"
    }
  },
  {
    "data": {
      "id": "2",
      "label": "Device 1",
      "type": "device"
    }
  },
  {
    "data": {
      "id": "3",
      "label": "IP 2",
      "type": "ip"
    }
  },
  {
    "data": {
      "id": "4",
      "label": "Device 2",
      "type": "device"
    }
  },
  {
    "data": {
      "id": "5",
      "label": "Device 3",
      "type": "device"
    }
  },
  {
    "data": {
      "id": "6",
      "label": "IP 3",
      "type": "ip"
    }
  },
  {
    "data": {
      "id": "7",
      "label": "Device 5",
      "type": "device"
    }
  },
  {
    "data": {
      "id": "8",
      "label": "Device 6",
      "type": "device"
    }
  },
  {
    "data": {
      "id": "9",
      "label": "Device 7",
      "type": "device"
    }
  },
  {
    "data": {
      "id": "10",
      "label": "Device 8",
      "type": "device"
    }
  },
  {
    "data": {
      "id": "11",
      "label": "Device 9",
      "type": "device"
    }
  },
  {
    "data": {
      "id": "12",
      "label": "IP 3",
      "type": "ip"
    }
  },
  {
    "data": {
      "id": "13",
      "label": "Device 10",
      "type": "device"
    }
  }
]